homo/__init__.py
homo/lab/__init__.py
homo/lab/__main__.py
homo/libhoyolab/__init__.py
homo/libhoyolab/accountLogin.py
homo/libhoyolab/libhoyolab.py
homo/libhoyolab/replace_regex.py
homo/libhoyolab/threadRender.py
homo/libhoyolab/urls.py
HoMoLab-0.9.5.3.1.dist-info/LICENSE
HoMoLab-0.9.5.3.1.dist-info/METADATA
HoMoLab-0.9.5.3.1.dist-info/WHEEL
HoMoLab-0.9.5.3.1.dist-info/entry_points.txt
HoMoLab-0.9.5.3.1.dist-info/top_level.txt
HoMoLab-0.9.5.3.1.dist-info/zip-safe
HoMoLab-0.9.5.3.1.dist-info/RECORD
