Metadata-Version: 2.1
Name: HoMoLab
Version: 0.9.5.3.1
Summary: 基于Pywebview的米游社PC客户端实现
Home-page: https://homolab.error063.work/
Author: Error063
Author-email: admin@error063.work
License: GPL3
Keywords: HoYoLab,米游社
Classifier: Programming Language :: Python :: 3
Classifier: License :: OSI Approved :: GNU General Public License v3 (GPLv3)
Classifier: Operating System :: OS Independent
Requires-Python: ~=3.10
License-File: LICENSE
Requires-Dist: altgraph (==0.17.3)
Requires-Dist: bleach (==6.0.0)
Requires-Dist: blinker (==1.6.2)
Requires-Dist: bottle (==0.12.25)
Requires-Dist: certifi (==2023.5.7)
Requires-Dist: cffi (==1.15.1)
Requires-Dist: charset-normalizer (==3.2.0)
Requires-Dist: click (==8.1.4)
Requires-Dist: clr-loader (==0.2.5)
Requires-Dist: colorama (==0.4.6)
Requires-Dist: cssutils (==1.0.2)
Requires-Dist: diff-match-patch (==20181111)
Requires-Dist: docutils (==0.20.1)
Requires-Dist: dominate (==2.8.0)
Requires-Dist: Flask (==2.3.2)
Requires-Dist: idna (==3.4)
Requires-Dist: importlib-metadata (==6.8.0)
Requires-Dist: itsdangerous (==2.1.2)
Requires-Dist: jaraco.classes (==3.3.0)
Requires-Dist: Jinja2 (==3.1.2)
Requires-Dist: keyring (==24.2.0)
Requires-Dist: lxml (==4.9.3)
Requires-Dist: markdown-it-py (==3.0.0)
Requires-Dist: MarkupSafe (==2.1.3)
Requires-Dist: mdurl (==0.1.2)
Requires-Dist: more-itertools (==10.1.0)
Requires-Dist: pefile (==2023.2.7)
Requires-Dist: pkginfo (==1.9.6)
Requires-Dist: proxy-tools (==0.1.0)
Requires-Dist: pycparser (==2.21)
Requires-Dist: Pygments (==2.16.1)
Requires-Dist: pyinstaller (==5.13.0)
Requires-Dist: pyinstaller-hooks-contrib (==2023.6)
Requires-Dist: pythonnet (==3.0.1)
Requires-Dist: pywebview (==4.2.2)
Requires-Dist: pywin32-ctypes (==0.2.2)
Requires-Dist: quill-delta (==1.0.3)
Requires-Dist: readme-renderer (==40.0)
Requires-Dist: requests (==2.31.0)
Requires-Dist: requests-toolbelt (==1.0.0)
Requires-Dist: rfc3986 (==2.0.0)
Requires-Dist: rich (==13.5.2)
Requires-Dist: six (==1.16.0)
Requires-Dist: twine (==4.0.2)
Requires-Dist: typing-extensions (==4.7.1)
Requires-Dist: ua-parser (==0.18.0)
Requires-Dist: urllib3 (==2.0.3)
Requires-Dist: user-agents (==2.2.0)
Requires-Dist: webencodings (==0.5.1)
Requires-Dist: Werkzeug (==2.3.6)
Requires-Dist: zipp (==3.16.2)
